{
"status":0,
"photos":[
{
"width":2884,
"height":3489,
"id":"there-is-always-a-bright-side",
"account":{
"id":"iborsch",
"is_vip":false,
"is_company":false,
"is_story_author":false,
"can_write_tip":true,
"in_club":false,
"introduction":"Follow me on Instagram! New posts every week https://www.instagram.com/borsch/",
"followers_count":727,
"resources_count":89,
"honor_score":1581,
"is_follow":false,
"avatar":"https://cdn-usa.skypixel.com/uploads/usa_files/account/avatar_image/769cb31e-9477-41d3-a4f1-93b20450afbe.png",
"name":"iborsch"
},
"club_wrok":false,
"type":"photo",
"image":"https://cdn-usa.skypixel.com/uploads/usa_files/photo/image/54ad9946-e0f9-44c1-8cf2-f02b1181ec6b.jpg",
"is_pano":false,
"is_360":false,
"badges":[
{
"name":"ordinary",
"image_name":"ordinary",
"en_description":"Staff Pick",
"cn_description":"精选作品",
"id":47
}
],
"likes_count":6,
"favorites_count":4,
"views_count":168,
"comments_count":1,
"image_status":null,
"title":"There is always a bright side"
},
{
"width":3980,
"height":2242,
"id":"jpg-99a4c5df-c8e7-4b76-80cc-0b9987503a93",
"account":{
"id":"10983587",
"is_vip":false,
"is_company":false,
"is_story_author":false,
"can_write_tip":false,
"in_club":false,
"introduction":"http://weibo.com/1892011334",
"followers_count":58,
"resources_count":175,
"honor_score":480,
"is_follow":false,
"avatar":"https://cdn-hz.skypixel.com/uploads/cn_files/account/avatar_image/d0a23297-6dfc-47b2-8b64-db1e5af32e1d.png",
"name":"Ryne_Wu"
},
"club_wrok":false,
"type":"photo",
"image":"https://cdn-hz.skypixel.com/uploads/cn_files/photo/image/6470382e-69ab-4b3e-991f-c16442d20415.JPG",
"is_pano":false,
"is_360":false,
"badges":[
{
"name":"ordinary",
"image_name":"ordinary",
"en_description":"Staff Pick",
"cn_description":"精选作品",
"id":47
}
],
"likes_count":64,
"favorites_count":9,
"views_count":1303,
"comments_count":13,
"image_status":null,
"title":"雅西.JPG"
},
{
"width":1239,
"height":696,
"id":"dji-bad02789-0131-442d-833e-79a4fddcecf9",
"account":{
"id":"285884319",
"is_vip":false,
"is_company":false,
"is_story_author":false,
"can_write_tip":false,
"in_club":false,
"introduction":null,
"followers_count":23,
"resources_count":64,
"honor_score":380,
"is_follow":false,
"avatar":"https://cdn-hz.skypixel.com/uploads/cn_files/account/avatar_image/26f4160f-d346-462b-988d-d649c7c896f3.png",
"name":"上帝之光"
},
"club_wrok":false,
"type":"photo",
"image":"https://cdn-hz.skypixel.com/uploads/cn_files/photo/image/3067af4d-e87c-40a2-891c-12c61406605f.jpg",
"is_pano":false,
"is_360":false,
"badges":[
{
"name":"ordinary",
"image_name":"ordinary",
"en_description":"Staff Pick",
"cn_description":"精选作品",
"id":47
}
],
"likes_count":24,
"favorites_count":0,
"views_count":563,
"comments_count":null,
"image_status":null,
"title":"印尼蓝梦岛梦幻沙滩"
},
{
"width":1024,
"height":1024,
"id":"dbee18ac-ca5a-48b9-9cf2-fd6c7b33d7ed",
"account":{
"id":"feng-jiang",
"is_vip":true,
"is_company":false,
"is_story_author":true,
"can_write_tip":true,
"in_club":true,
"introduction":"a new vision of the world ",
"followers_count":872,
"resources_count":212,
"honor_score":3058,
"is_follow":false,
"avatar":"https://cdn-usa.skypixel.com/uploads/usa_files/account/avatar_image/4c247141-a808-4a6d-ab95-c20a69eac097.png",
"name":"FENG JIANG"
},
"club_wrok":false,
"type":"photo",
"image":"https://cdn-usa.skypixel.com/uploads/usa_files/photo/image/5a1de24a-9641-4af2-87f5-d77ca7c0e4f7.jpg",
"is_pano":false,
"is_360":true,
"badges":[
{
"name":"ordinary",
"image_name":"ordinary",
"en_description":"Staff Pick",
"cn_description":"精选作品",
"id":47
}
],
"likes_count":90,
"favorites_count":16,
"views_count":17666,
"comments_count":10,
"image_status":"available",
"title":"白马咀"
},
{
"width":1638,
"height":2048,
"id":"the-stairway-to-heaven",
"account":{
"id":"bensava",
"is_vip":false,
"is_company":false,
"is_story_author":false,
"can_write_tip":true,
"in_club":false,
"introduction":"Instagram 》ben.savage\r\n\r\nWelcome to my gallery \r\n\r\nThe shots below consist of the adventures i have been on over the past 6 months ",
"followers_count":462,
"resources_count":60,
"honor_score":917,
"is_follow":false,
"avatar":"https://cdn-usa.skypixel.com/uploads/usa_files/account/avatar_image/b687dcb3-9975-441d-b633-9348f395092c.png",
"name":"Ben Savage "
},
"club_wrok":false,
"type":"photo",
"image":"https://cdn-usa.skypixel.com/uploads/usa_files/photo/image/351dcce3-6ee2-40dd-bda9-c12e868b7a85.jpg",
"is_pano":false,
"is_360":false,
"badges":[
{
"name":"ordinary",
"image_name":"ordinary",
"en_description":"Staff Pick",
"cn_description":"精选作品",
"id":47
}
],
"likes_count":91,
"favorites_count":15,
"views_count":3190,
"comments_count":2,
"image_status":null,
"title":"THE STAIRWAY TO HEAVEN "
},
{
"width":1024,
"height":1024,
"id":"02da2ae1-5c37-4c74-aed5-b955348309f1",
"account":{
"id":"wongchi-2d912f7b-3a08-4ba1-8f88-f55643b7d9a7",
"is_vip":false,
"is_company":false,
"is_story_author":false,
"can_write_tip":true,
"in_club":true,
"introduction":"",
"followers_count":183,
"resources_count":157,
"honor_score":773,
"is_follow":false,
"avatar":"https://cdn-usa.skypixel.com/uploads/usa_files/default_images/default_avatar/99e9657e-0b4b-4547-9e9f-7f0bf6cc5cca.png",
"name":"wongchi..."
},
"club_wrok":false,
"type":"photo",
"image":"https://cdn-usa.skypixel.com/uploads/usa_files/photo/image/3533adb5-1e3c-470e-bd87-b9f30e05663b.jpg",
"is_pano":false,
"is_360":true,
"badges":[
{
"name":"ordinary",
"image_name":"ordinary",
"en_description":"Staff Pick",
"cn_description":"精选作品",
"id":47
}
],
"likes_count":93,
"favorites_count":13,
"views_count":14587,
"comments_count":13,
"image_status":"available",
"title":"Tai Lam Chung Reservoir(屯門大欖涌水塘), Tuen Mun, NT, HK."
},
{
"width":1600,
"height":1200,
"id":"mt-huangzui",
"account":{
"id":"05p51-ttia",
"is_vip":false,
"is_company":false,
"is_story_author":false,
"can_write_tip":true,
"in_club":true,
"introduction":"I Love The Sky! ",
"followers_count":354,
"resources_count":107,
"honor_score":1334,
"is_follow":false,
"avatar":"https://cdn-usa.skypixel.com/uploads/usa_files/account/avatar_image/9cdb667a-dee6-4dde-bd0a-4d9859383e45.jpg",
"name":"05P51 / TTIA"
},
"club_wrok":false,
"type":"photo",
"image":"https://cdn-usa.skypixel.com/uploads/usa_files/photo/image/24967029-8890-47d2-99e9-f896bb55ea6b.JPG",
"is_pano":false,
"is_360":false,
"badges":[
{
"name":"ordinary",
"image_name":"ordinary",
"en_description":"Staff Pick",
"cn_description":"精选作品",
"id":47
}
],
"likes_count":101,
"favorites_count":17,
"views_count":3825,
"comments_count":4,
"image_status":null,
"title":"Mt. Huangzui "
},
{
"width":1920,
"height":1211,
"id":"40ced063-c0e1-45d8-9c3a-a800e8a209f8",
"account":{
"id":"364b993d-6d88-4849-8f76-91c4ea78c4c6",
"is_vip":true,
"is_company":false,
"is_story_author":true,
"can_write_tip":true,
"in_club":true,
"introduction":"善于设计，摄影，影视后期，最近迷上航拍",
"followers_count":953,
"resources_count":77,
"honor_score":2724,
"is_follow":false,
"avatar":"https://cdn-usa.skypixel.com/uploads/usa_files/account/avatar_image/ac24f313-4752-4003-9a39-d8919a3a014e.jpg",
"name":"武汉的火星人 "
},
"club_wrok":false,
"type":"photo",
"image":"https://cdn-hz.skypixel.com/uploads/cn_files/photo/image/a8fb52c0-71d8-47b2-8f77-9f5eabe966ec.jpg",
"is_pano":false,
"is_360":false,
"badges":[
{
"name":"ordinary",
"image_name":"ordinary",
"en_description":"Staff Pick",
"cn_description":"精选作品",
"id":47
}
],
"likes_count":163,
"favorites_count":23,
"views_count":4701,
"comments_count":9,
"image_status":null,
"title":"三峡人家"
},
{
"width":4916,
"height":2822,
"id":"stacked-3548f853-2e55-44dc-8cf9-dff19f13e2b2",
"account":{
"id":"ericdimsum_user",
"is_vip":false,
"is_company":false,
"is_story_author":false,
"can_write_tip":true,
"in_club":true,
"introduction":"VFX Artist, Creator of 3D Environments, Aerial VideoGraphy and Photography enthusiast\r\n",
"followers_count":325,
"resources_count":30,
"honor_score":624,
"is_follow":false,
"avatar":"https://cdn-usa.skypixel.com/uploads/usa_files/account/avatar_image/33015192-ad5d-43aa-8b3f-60cea39fb1e2.jpg",
"name":"Eric Dima-ala"
},
"club_wrok":false,
"type":"photo",
"image":"https://cdn-usa.skypixel.com/uploads/usa_files/photo/image/03d8be7d-ea44-46d7-9dfd-96dd7276e42e.jpg",
"is_pano":false,
"is_360":false,
"badges":[
{
"name":"ordinary",
"image_name":"ordinary",
"en_description":"Staff Pick",
"cn_description":"精选作品",
"id":47
}
],
"likes_count":96,
"favorites_count":18,
"views_count":2119,
"comments_count":null,
"image_status":null,
"title":"Stacked"
},
{
"width":3846,
"height":4445,
"id":"beach-head-13005eed-1649-42e7-8a07-012d47c09147",
"account":{
"id":"ericdimsum_user",
"is_vip":false,
"is_company":false,
"is_story_author":false,
"can_write_tip":true,
"in_club":true,
"introduction":"VFX Artist, Creator of 3D Environments, Aerial VideoGraphy and Photography enthusiast\r\n",
"followers_count":325,
"resources_count":30,
"honor_score":624,
"is_follow":false,
"avatar":"https://cdn-usa.skypixel.com/uploads/usa_files/account/avatar_image/33015192-ad5d-43aa-8b3f-60cea39fb1e2.jpg",
"name":"Eric Dima-ala"
},
"club_wrok":false,
"type":"photo",
"image":"https://cdn-usa.skypixel.com/uploads/usa_files/photo/image/b57f0d0f-ba22-484b-bb69-187a293b5486.jpg",
"is_pano":false,
"is_360":false,
"badges":[
{
"name":"ordinary",
"image_name":"ordinary",
"en_description":"Staff Pick",
"cn_description":"精选作品",
"id":47
}
],
"likes_count":77,
"favorites_count":9,
"views_count":1628,
"comments_count":3,
"image_status":null,
"title":"Beach Head"
},
{
"width":5120,
"height":2880,
"id":"screen-shot-2017-04-08-at-20-53-42-jpg",
"account":{
"id":"rich298",
"is_vip":false,
"is_company":false,
"is_story_author":false,
"can_write_tip":true,
"in_club":false,
"introduction":null,
"followers_count":50,
"resources_count":80,
"honor_score":1384,
"is_follow":false,
"avatar":"https://cdn-usa.skypixel.com/uploads/usa_files/account/avatar_image/d11826d0-06f5-4a6b-8081-8e1d25478467.PNG",
"name":"Richard Armfield"
},
"club_wrok":false,
"type":"photo",
"image":"https://cdn-usa.skypixel.com/uploads/usa_files/photo/image/8f4e057b-6f4d-43dc-90f2-b1205985a57f.jpg",
"is_pano":false,
"is_360":false,
"badges":[
{
"name":"ordinary",
"image_name":"ordinary",
"en_description":"Staff Pick",
"cn_description":"精选作品",
"id":47
}
],
"likes_count":91,
"favorites_count":9,
"views_count":1682,
"comments_count":3,
"image_status":null,
"title":"Ennerdale Water"
},
{
"width":3715,
"height":2047,
"id":"castaway-c8bc742e-02cc-4655-84e2-fbf3734a72af",
"account":{
"id":"andy3791",
"is_vip":false,
"is_company":false,
"is_story_author":false,
"can_write_tip":true,
"in_club":true,
"introduction":"Got my 1st Phantom January 2016\r\nKeen photographer a Getty images contributor.....\r\n\r\nhttps://www.flickr.com/photos/andrew_thomas_73/\r\n\r\n\r\n\r\n\r\n\r\n",
"followers_count":1215,
"resources_count":54,
"honor_score":1768,
"is_follow":false,
"avatar":"https://cdn-usa.skypixel.com/uploads/usa_files/account/avatar_image/e74e63f7-d3c9-4aa2-a58d-7fc02f0e0c58.jpg",
"name":"Andrew Thomas"
},
"club_wrok":false,
"type":"photo",
"image":"https://cdn-usa.skypixel.com/uploads/usa_files/photo/image/d9f10edb-df7f-4057-b7b8-de558ffd6c75.jpg",
"is_pano":false,
"is_360":false,
"badges":[
{
"name":"ordinary",
"image_name":"ordinary",
"en_description":"Staff Pick",
"cn_description":"精选作品",
"id":47
}
],
"likes_count":117,
"favorites_count":18,
"views_count":1548,
"comments_count":2,
"image_status":null,
"title":"Castaway"
}
],
"videos":[
{
"id":"d3ababe3-7f59-47e1-933d-6929797befdb",
"account":{
"id":"jcourtial_user",
"is_vip":false,
"is_company":false,
"is_story_author":false,
"can_write_tip":true,
"in_club":false,
"introduction":"I\"m a travel photographer from the south of France, based in London. My drone photography was featured in DJI's book  'Above the world', and published in magazines like Digital Photo magazine, The Times, Time magazine, National Geographic, etc.\r\nI created a Youtube channel dedicated to drone photography, with tips and inspiration:\r\nhttp://masterdronephotography.com/\r\n",
"followers_count":849,
"resources_count":54,
"honor_score":1446,
"is_follow":false,
"avatar":"https://cdn-usa.skypixel.com/uploads/usa_files/account/avatar_image/b745b28c-c940-4835-9864-cfcf03efc7c6.png",
"name":"jerome courtial"
},
"type":"video",
"provider":"vip",
"embed_url":"https://www.djivideos.com/video_play/771edf7d-90de-48f0-b35c-16886aa61324",
"duration":"01:02",
"badges":[
{
"name":"ordinary",
"image_name":"ordinary",
"en_description":"Staff Pick",
"cn_description":"精选作品",
"id":47
}
],
"title":"Run Ibiza!",
"likes_count":4,
"favorites_count":0,
"views_count":277,
"comments_count":null,
"image":"https://cdn-usa.skypixel.com/uploads/usa_files/video/image/061e0e55-056e-4d13-a571-8f8075dcd42f.jpg",
"club_wrok":false
},
{
"id":"c6a0d26f-c08b-43bd-9b4a-3d9ee68b0b8f",
"account":{
"id":"nothing826",
"is_vip":false,
"is_company":false,
"is_story_author":true,
"can_write_tip":true,
"in_club":true,
"introduction":null,
"followers_count":613,
"resources_count":115,
"honor_score":1234,
"is_follow":false,
"avatar":"https://cdn-hz.skypixel.com/uploads/cn_files/account/avatar_image/c8cd6815-f559-4247-a07c-125c4700bf57.png",
"name":"李珩 13811278527"
},
"type":"video",
"provider":"vip",
"embed_url":"https://www.djivideos.com/video_play/217d05fb-5a04-4d8c-a788-ebef2e796b1f",
"duration":"03:49",
"badges":[
{
"name":"ordinary",
"image_name":"ordinary",
"en_description":"Staff Pick",
"cn_description":"精选作品",
"id":47
}
],
"title":"冰川－遇见世界尽头",
"likes_count":3,
"favorites_count":0,
"views_count":248,
"comments_count":null,
"image":"https://cdn-hz.skypixel.com/uploads/cn_files/video/image/763c0184-9b43-422c-9713-6897284a258a.jpg",
"club_wrok":false
},
{
"id":"a71f6a8d-3670-4334-baad-97381afa905b",
"account":{
"id":"nothing826",
"is_vip":false,
"is_company":false,
"is_story_author":true,
"can_write_tip":true,
"in_club":true,
"introduction":null,
"followers_count":613,
"resources_count":115,
"honor_score":1234,
"is_follow":false,
"avatar":"https://cdn-hz.skypixel.com/uploads/cn_files/account/avatar_image/c8cd6815-f559-4247-a07c-125c4700bf57.png",
"name":"李珩 13811278527"
},
"type":"video",
"provider":"vip",
"embed_url":"https://www.djivideos.com/video_play/7fa706f9-db83-4288-b099-74b57d6f2ecf",
"duration":"04:02",
"badges":[
{
"name":"ordinary",
"image_name":"ordinary",
"en_description":"Staff Pick",
"cn_description":"精选作品",
"id":47
}
],
"title":"攀登那玛峰（4min）",
"likes_count":3,
"favorites_count":1,
"views_count":142,
"comments_count":null,
"image":"https://cdn-hz.skypixel.com/uploads/cn_files/video/image/51b8f765-9549-4d44-9b6e-ea16acfd9c26.jpg",
"club_wrok":false
},
{
"id":"62637a19-4301-478c-a520-67c4cd5edb61",
"account":{
"id":"djistor-61a46247-49d8-4204-a10a-d2bf74b9f003",
"is_vip":false,
"is_company":false,
"is_story_author":false,
"can_write_tip":true,
"in_club":true,
"introduction":"Hey there, I'm Cody. One day I decided to try combining my running passion with my drone hobby. This is the result!",
"followers_count":683,
"resources_count":38,
"honor_score":612,
"is_follow":false,
"avatar":"https://cdn-usa.skypixel.com/uploads/usa_files/account/avatar_image/2db0969a-d513-490e-80a3-3193e1152371.png",
"name":"High Flying Runner"
},
"type":"video",
"provider":"vip",
"embed_url":"https://www.djivideos.com/video_play/8007ae71-1955-4159-a47d-d76457264327",
"duration":"00:48",
"badges":[
{
"name":"ordinary",
"image_name":"ordinary",
"en_description":"Staff Pick",
"cn_description":"精选作品",
"id":47
}
],
"title":"HighFlyingRunner: June 2017",
"likes_count":3,
"favorites_count":0,
"views_count":165,
"comments_count":null,
"image":"https://cdn-usa.skypixel.com/uploads/usa_files/video/image/5afbff65-5567-4cea-93ec-19082e3ddd12.jpg",
"club_wrok":false
},
{
"id":"31e88899-df03-4c14-a7b6-8d1d0fdfad84",
"account":{
"id":"4050208",
"is_vip":false,
"is_company":false,
"is_story_author":false,
"can_write_tip":false,
"in_club":false,
"introduction":null,
"followers_count":124,
"resources_count":29,
"honor_score":187,
"is_follow":false,
"avatar":"https://cdn-hz.skypixel.com/uploads/cn_files/account/avatar_image/a6b8c27d-64e2-453b-943e-0fe42bc40f88.png",
"name":"4050208"
},
"type":"video",
"provider":"vip",
"embed_url":"https://www.djivideos.com/video_play/73a0c21d-4718-40b3-b266-bac3e22a061c",
"duration":"05:03",
"badges":[
{
"name":"ordinary",
"image_name":"ordinary",
"en_description":"Staff Pick",
"cn_description":"精选作品",
"id":47
}
],
"title":"Northwest China",
"likes_count":29,
"favorites_count":7,
"views_count":3120,
"comments_count":5,
"image":"https://cdn-hz.skypixel.com/uploads/cn_files/video/image/bcdd4866-49cc-4f7c-b68d-defd93e9f0f3.jpg",
"club_wrok":false
},
{
"id":"d6b0d2ac-a173-465a-a586-4f9f36d30dcb",
"account":{
"id":"199622_user",
"is_vip":false,
"is_company":false,
"is_story_author":false,
"can_write_tip":true,
"in_club":false,
"introduction":null,
"followers_count":222,
"resources_count":30,
"honor_score":663,
"is_follow":false,
"avatar":"https://cdn-usa.skypixel.com/uploads/usa_files/account/avatar_image/477b7f2e-9fb0-46f9-9d9b-dbf5559c47ed.png",
"name":"零 大魔王"
},
"type":"video",
"provider":"vip",
"embed_url":"https://www.djivideos.com/video_play/8fdc7e9a-e797-459b-9c0a-a39b1ac0b5ee",
"duration":"03:28",
"badges":[
{
"name":"ordinary",
"image_name":"ordinary",
"en_description":"Staff Pick",
"cn_description":"精选作品",
"id":47
}
],
"title":"从达洛尔到乞力马扎罗-东非行记",
"likes_count":25,
"favorites_count":0,
"views_count":9987,
"comments_count":4,
"image":"https://cdn-hz.skypixel.com/uploads/cn_files/video/image/87d250e2-dfaa-4b77-b70c-98efd3030250.JPG",
"club_wrok":false
},
{
"id":"0aa5d880-b83d-44c8-962c-2b13ca796bbd",
"account":{
"id":"danster",
"is_vip":false,
"is_company":false,
"is_story_author":false,
"can_write_tip":false,
"in_club":false,
"introduction":null,
"followers_count":9,
"resources_count":1,
"honor_score":65,
"is_follow":false,
"avatar":"https://cdn-usa.skypixel.com/uploads/usa_files/default_images/default_avatar/99e9657e-0b4b-4547-9e9f-7f0bf6cc5cca.png",
"name":"dansterenson"
},
"type":"video",
"provider":"vip",
"embed_url":"https://www.djivideos.com/video_play/a9be704b-c621-4f76-a409-4330b5108b1a",
"duration":"04:15",
"badges":[
{
"name":"ordinary",
"image_name":"ordinary",
"en_description":"Staff Pick",
"cn_description":"精选作品",
"id":47
}
],
"title":"New Zealand Road Trip",
"likes_count":30,
"favorites_count":3,
"views_count":1981,
"comments_count":2,
"image":"https://cdn-usa.skypixel.com/uploads/usa_files/video/image/a1a901d0-404f-428f-928c-f2bf2d31acc3.jpg",
"club_wrok":false
},
{
"id":"10b01e75-eae7-4d88-861c-0de00be58e6e",
"account":{
"id":"pedromo-966fced3-6ae2-47c0-a9db-3826b8901327",
"is_vip":false,
"is_company":false,
"is_story_author":false,
"can_write_tip":false,
"in_club":false,
"introduction":"Eternizando momentos!",
"followers_count":22,
"resources_count":9,
"honor_score":130,
"is_follow":false,
"avatar":"https://cdn-usa.skypixel.com/uploads/usa_files/account/avatar_image/46981f37-bdd4-473c-8222-d8ba492fd433.jpg",
"name":"Pedro Luz"
},
"type":"video",
"provider":"vip",
"embed_url":"https://www.djivideos.com/video_play/c70b9970-aafa-40bd-96fa-c9f9a163c758",
"duration":"02:18",
"badges":[
{
"name":"ordinary",
"image_name":"ordinary",
"en_description":"Staff Pick",
"cn_description":"精选作品",
"id":47
}
],
"title":"EXTREME HIGHLINE BRASIL - VINICIUS CAUHY",
"likes_count":18,
"favorites_count":2,
"views_count":1029,
"comments_count":1,
"image":"https://cdn-usa.skypixel.com/uploads/usa_files/video/image/f57cccd5-ac81-4c94-8fdf-f18288059c2d.jpg",
"club_wrok":false
},
{
"id":"964c8006-ce36-4bed-a9df-99997aff6b10",
"account":{
"id":"arvids-3f355996-279c-4815-b415-0cea613eb87a",
"is_vip":false,
"is_company":false,
"is_story_author":false,
"can_write_tip":false,
"in_club":false,
"introduction":"Moved by Outdoors",
"followers_count":8,
"resources_count":10,
"honor_score":114,
"is_follow":false,
"avatar":"https://cdn-usa.skypixel.com/uploads/usa_files/account/avatar_image/138c8e52-db5a-4ab9-b0cc-3fa968545f6a.png",
"name":"Eaglewood Films"
},
"type":"video",
"provider":"vip",
"embed_url":"https://www.djivideos.com/video_play/9ad0bb44-73c4-44ec-a42c-be36cc57fcc2",
"duration":"04:01",
"badges":[
{
"name":"ordinary",
"image_name":"ordinary",
"en_description":"Staff Pick",
"cn_description":"精选作品",
"id":47
}
],
"title":"Portugal: On the Edge of the World",
"likes_count":7,
"favorites_count":1,
"views_count":599,
"comments_count":3,
"image":"https://cdn-usa.skypixel.com/uploads/usa_files/video/image/d5947885-e834-4932-b0cc-1347834556c0.jpg",
"club_wrok":false
},
{
"id":"0f702322-ca85-4ec7-8fa6-b034968305ef",
"account":{
"id":"fujiabra",
"is_vip":false,
"is_company":false,
"is_story_author":false,
"can_write_tip":false,
"in_club":false,
"introduction":"",
"followers_count":2,
"resources_count":3,
"honor_score":59,
"is_follow":false,
"avatar":"https://cdn-usa.skypixel.com/uploads/usa_files/account/avatar_image/b5eae29b-aaa7-42e1-9f0f-f95307ac5e71.gif",
"name":"Fujiabra Films"
},
"type":"video",
"provider":"vip",
"embed_url":"https://www.djivideos.com/video_play/4c0186b1-c80d-46f4-bdf2-98904dc0836a",
"duration":"02:09",
"badges":[
{
"name":"ordinary",
"image_name":"ordinary",
"en_description":"Staff Pick",
"cn_description":"精选作品",
"id":47
}
],
"title":"Canadian Nature",
"likes_count":7,
"favorites_count":0,
"views_count":450,
"comments_count":1,
"image":"https://cdn-usa.skypixel.com/uploads/usa_files/video/image/f9fa9903-f0fc-43f1-993f-666a7efce43d.jpg",
"club_wrok":false
},
{
"id":"1c8e0ce5-4193-4cb5-95cc-9f4e018b683a",
"account":{
"id":"r_audrius",
"is_vip":false,
"is_company":false,
"is_story_author":false,
"can_write_tip":true,
"in_club":false,
"introduction":"Aerial video \u0026 photography\r\n     Hobby \u0026 business",
"followers_count":116,
"resources_count":20,
"honor_score":1349,
"is_follow":false,
"avatar":"https://cdn-usa.skypixel.com/uploads/usa_files/account/avatar_image/4044155a-4e42-4910-a44b-ea594df2edd4.png",
"name":"Audrius R"
},
"type":"video",
"provider":"vip",
"embed_url":"https://www.djivideos.com/video_play/46143799-a4db-4ee6-b8fb-484f1adea465",
"duration":"03:07",
"badges":[
{
"name":"ordinary",
"image_name":"ordinary",
"en_description":"Staff Pick",
"cn_description":"精选作品",
"id":47
}
],
"title":"Sleeping valley sunrise / Frafjord  / Norway",
"likes_count":114,
"favorites_count":30,
"views_count":8215,
"comments_count":7,
"image":"https://cdn-usa.skypixel.com/uploads/usa_files/video/image/19911a7b-3cfd-468b-bce1-d6cdee591055.JPG",
"club_wrok":false
},
{
"id":"2c54b635-78d7-438d-b851-f165cd2125ee",
"account":{
"id":"chad-m-46845924-3f02-4cb1-9c84-759220c644db",
"is_vip":false,
"is_company":false,
"is_story_author":false,
"can_write_tip":false,
"in_club":false,
"introduction":null,
"followers_count":1,
"resources_count":3,
"honor_score":55,
"is_follow":false,
"avatar":"https://cdn-usa.skypixel.com/uploads/usa_files/default_images/default_avatar/99e9657e-0b4b-4547-9e9f-7f0bf6cc5cca.png",
"name":"chadm1984"
},
"type":"video",
"provider":"vip",
"embed_url":"https://www.djivideos.com/video_play/9c6e6921-2814-4241-922d-2f3e0bba74cf",
"duration":"03:01",
"badges":[
{
"name":"ordinary",
"image_name":"ordinary",
"en_description":"Staff Pick",
"cn_description":"精选作品",
"id":47
}
],
"title":"Spain by Drone",
"likes_count":4,
"favorites_count":2,
"views_count":991,
"comments_count":null,
"image":"https://cdn-usa.skypixel.com/uploads/usa_files/video/image/4777c905-4a96-4ad0-a7af-55fdd0f9ae92.jpg",
"club_wrok":false
}
],
"panos":[
{
"width":5532,
"height":1879,
"id":"torre-di-catilina-v3-pistoia-tuscany-italy",
"account":{
"id":"lorenzo-marianeschi",
"is_vip":false,
"is_company":false,
"is_story_author":false,
"can_write_tip":true,
"in_club":true,
"introduction":"Video, Photography, Drones and Life lover from Pistoia, Tuscany - Italy.",
"followers_count":446,
"resources_count":31,
"honor_score":907,
"is_follow":false,
"avatar":"https://cdn-usa.skypixel.com/uploads/usa_files/account/avatar_image/29ccac37-8003-48c5-bff4-7bc2a6d81220.png",
"name":"Lorenzo Marianeschi"
},
"club_wrok":false,
"type":"photo",
"image":"https://cdn-usa.skypixel.com/uploads/usa_files/photo/image/40e078b4-29d5-4d89-abf0-4ee38c620d1e.JPG",
"is_pano":true,
"is_360":false,
"badges":[
{
"name":"ordinary",
"image_name":"ordinary",
"en_description":"Staff Pick",
"cn_description":"精选作品",
"id":47
}
],
"likes_count":185,
"favorites_count":49,
"views_count":6714,
"comments_count":19,
"image_status":null,
"title":"Torre di Catilina v3 - Pistoia, Tuscany - Italy"
},
{
"width":6660,
"height":2176,
"id":"lovely-tuscany-s-road",
"account":{
"id":"testsrls14",
"is_vip":true,
"is_company":false,
"is_story_author":false,
"can_write_tip":true,
"in_club":true,
"introduction":"Brothers based in Tuscany, Italy. Our passion grow to become our business. Content marketing, videomaking, aerial/ground photography and filming. ",
"followers_count":1303,
"resources_count":116,
"honor_score":3711,
"is_follow":false,
"avatar":"https://cdn-usa.skypixel.com/uploads/usa_files/account/avatar_image/ae4e4ec6-16d7-40a4-9f3b-0b9d00898202.jpg",
"name":"Yasser \u0026 Amir Lashin"
},
"club_wrok":false,
"type":"photo",
"image":"https://cdn-usa.skypixel.com/uploads/usa_files/photo/image/fa5a8f37-f6ec-439d-9262-a8580516cb7b.jpg",
"is_pano":true,
"is_360":false,
"badges":[
{
"name":"ordinary",
"image_name":"ordinary",
"en_description":"Staff Pick",
"cn_description":"精选作品",
"id":47
}
],
"likes_count":171,
"favorites_count":31,
"views_count":4452,
"comments_count":3,
"image_status":null,
"title":"Lovely Tuscany's road"
}
]
}
